uno_log/__init__.py
uno_log-0.2.0.dist-info/LICENSE
uno_log-0.2.0.dist-info/METADATA
uno_log-0.2.0.dist-info/WHEEL
uno_log-0.2.0.dist-info/top_level.txt
uno_log-0.2.0.dist-info/RECORD
