Metadata-Version: 2.1
Name: uno-log
Version: 0.2.0
Summary: uno's logging library
Home-page: https://github.com/mentalsmash/uno-log
Author: mentalsmash.org
Author-email: support@mentalsmash.org
License: License :: OSI Approved :: Apache Software License
Platform: UNKNOWN
Classifier: Development Status :: 3 - Alpha
Classifier: Programming Language :: Python :: 3
Classifier: License :: OSI Approved :: Apache Software License
Requires-Python: >=3.6, <4
Requires-Dist: termcolor
